pyxray/__init__.py
pyxray/_version.py
pyxray/base.py
pyxray/cbook.py
pyxray/composition.py
pyxray/data.py
pyxray/descriptor.py
pyxray/property.py
pyxray/util.py
pyxray/data/campbell.asc
pyxray/data/carlson_subshell_ionization_data.csv
pyxray/data/dtsa_line.csv
pyxray/data/dtsa_subshell.csv
pyxray/data/krause_subshell_width_data.csv
pyxray/data/lambda.asc
pyxray/data/pyxray.db
pyxray/parser/__init__.py
pyxray/parser/base.py
pyxray/parser/campbell2001.py
pyxray/parser/dtsa.py
pyxray/parser/jeol.py
pyxray/parser/nist.py
pyxray/parser/notation.py
pyxray/parser/perkins1991.py
pyxray/parser/sargent_welch.py
pyxray/parser/wikipedia.py
pyxray/sql/__init__.py
pyxray/sql/base.py
pyxray/sql/build.py
pyxray/sql/data.py
pyxray-1.8.0.dist-info/LICENSE
pyxray-1.8.0.dist-info/METADATA
pyxray-1.8.0.dist-info/WHEEL
pyxray-1.8.0.dist-info/entry_points.txt
pyxray-1.8.0.dist-info/top_level.txt
pyxray-1.8.0.dist-info/RECORD
