Metadata-Version: 2.1
Name: pyxray
Version: 1.8.0
Summary: Definitions and properties of X-ray transitions
Home-page: https://github.com/openmicroanalysis/pyxray
Author: Philippe T. Pinard
Author-email: philippe.pinard@gmail.com
License: MIT license
Platform: UNKNOWN
Classifier: Development Status :: 4 - Beta
Classifier: Intended Audience :: End Users/Desktop
Classifier: License :: OSI Approved :: MIT License
Classifier: Natural Language :: English
Classifier: Programming Language :: Python
Classifier: Operating System :: OS Independent
Classifier: Topic :: Scientific/Engineering
Classifier: Topic :: Scientific/Engineering :: Physics
License-File: LICENSE
Requires-Dist: sqlalchemy
Requires-Dist: tabulate
Requires-Dist: tqdm
Requires-Dist: dataclasses ; python_version == "3.6.*"
Provides-Extra: dev
Requires-Dist: requests ; extra == 'dev'
Requires-Dist: requests-cache ; extra == 'dev'
Requires-Dist: sphinx ; extra == 'dev'
Provides-Extra: test
Requires-Dist: pytest ; extra == 'test'
Requires-Dist: pytest-cov ; extra == 'test'
